direct_connect/exceptions.py
direct_connect/nmdc/__init__.py
direct_connect/nmdc/client.py
direct_connect-0.1.2.dist-info/LICENSE.md
direct_connect-0.1.2.dist-info/METADATA
direct_connect-0.1.2.dist-info/WHEEL
direct_connect-0.1.2.dist-info/RECORD
